.coveragerc
.gitignore
.travis.yml
CONDUCT.md
CONTRIBUTING.md
LICENSE
MANIFEST.in
README.rst
VERSION
devRequirements.txt
requirements.txt
setup.cfg
setup.py
LOGO/osf-cli-logo-v1-small.png
LOGO/osf-cli-logo-v1.ai
LOGO/osf-cli-logo-v1.png
LOGO/osf-cli-logo-v1.svg
build_tools/travis_install.sh
dist/osfclient-denmanlab-0.0.1.tar.gz
dist/osfclient-denmanlab-0.0.2.tar.gz
dist/osfclient-denmanlab-0.0.3.tar.gz
dist/osfclient-denmanlab-0.0.4.tar.gz
dist/osfclient_denmanlab-0.0.2-py3.8.egg
docs/Makefile
docs/cli-usage.rst
docs/conf.py
docs/index.rst
docs/make.bat
docs/api/osfclient.rst
osfclient/__init__.py
osfclient/__main__.py
osfclient/__version__.py
osfclient/api.py
osfclient/cli.py
osfclient/exceptions.py
osfclient/utils.py
osfclient/../LICENSE
osfclient/../VERSION
osfclient/../requirements.txt
osfclient/models/__init__.py
osfclient/models/core.py
osfclient/models/file.py
osfclient/models/project.py
osfclient/models/session.py
osfclient/models/storage.py
osfclient/models/../../LICENSE
osfclient/models/../../VERSION
osfclient/models/../../requirements.txt
osfclient/tests/__init__.py
osfclient/tests/fake_responses.py
osfclient/tests/mocks.py
osfclient/tests/test_api.py
osfclient/tests/test_cli.py
osfclient/tests/test_cloning.py
osfclient/tests/test_fetching.py
osfclient/tests/test_file.py
osfclient/tests/test_listing.py
osfclient/tests/test_main.py
osfclient/tests/test_project.py
osfclient/tests/test_removing.py
osfclient/tests/test_session.py
osfclient/tests/test_storage.py
osfclient/tests/test_uploading.py
osfclient/tests/test_utils.py
osfclient/tests/../../LICENSE
osfclient/tests/../../VERSION
osfclient/tests/../../requirements.txt
osfclient_denmanlab.egg-info/PKG-INFO
osfclient_denmanlab.egg-info/SOURCES.txt
osfclient_denmanlab.egg-info/dependency_links.txt
osfclient_denmanlab.egg-info/entry_points.txt
osfclient_denmanlab.egg-info/requires.txt
osfclient_denmanlab.egg-info/top_level.txt