Metadata-Version: 1.1
Name: osfclient-denmanlab
Version: 0.0.5
Summary: An OSF command-line library extension for the denmanlab
Home-page: https://github.com/denmanlab/osfclient
Author: The OSF-cli authors; danieljdenman
Author-email: UNKNOWN
License: BSD3
Platform: UNKNOWN
Classifier: Development Status :: 3 - Alpha
Classifier: Environment :: Console
Classifier: Intended Audience :: Developers
Classifier: Intended Audience :: Science/Research
Classifier: Programming Language :: Python :: 3.8
Classifier: License :: OSI Approved :: BSD License
Classifier: Topic :: Utilities
